steams/__init__.py
steams/data/KVyQVx.py
steams/data/__init__.py
steams/models/__init__.py
steams/models/mads.py
steams/tepe/__init__.py
steams/tepe/steams.py
steams/tepe/tepe.py
steams/utils/__init__.py
steams/utils/criterion.py
steams/utils/model.py
steams/utils/scale.py
steams/utils/scheduler.py
steams/utils/utils.py
steams-0.18.dist-info/LICENSE
steams-0.18.dist-info/METADATA
steams-0.18.dist-info/WHEEL
steams-0.18.dist-info/top_level.txt
steams-0.18.dist-info/RECORD
