Metadata-Version: 2.1
Name: steams
Version: 0.18
Summary: Space-time prediction with sparse and irregular space-time multi-timeserie.
Home-page: https://git.nilu.no/aqdl/steams_pkg
Author: Jean-Marie Lepioufle
Author-email: Jean-Marie Lepioufle <jm@jeanmarie.eu>
License: MIT + Copyright NILU
Project-URL: Homepage, https://git.nilu.no/aqdl/steams_pkg
Classifier: Programming Language :: Python :: 3
Requires-Python: >=3.8
License-File: LICENSE
Requires-Dist: pandas (~=1.2.5)
Requires-Dist: torch (~=1.11)
Requires-Dist: numpy (~=1.23.3)
Provides-Extra: examples
Requires-Dist: ipython ; extra == 'examples'
Requires-Dist: jupyter ; extra == 'examples'
Requires-Dist: os ; extra == 'examples'
Requires-Dist: matplotlib ; extra == 'examples'
